[{"score":0,"score_max":1,"score_min":0,"flag":1,"level":1,"start_time":1766735940000,"end_time":1766735999000},{"score":0,"score_max":1,"score_min":0,"flag":1,"level":1,"start_time":1766735880000,"end_time":1766735939000},{"score":0,"score_max":1,"score_min":0,"flag":1,"level":1,"start_time":1766735820000,"end_time":1766735879000},{"score":1,"score_max":2,"score_min":1,"flag":1,"level":1,"start_time":1766735760000,"end_time":1766735819000},{"score":2,"score_max":2,"score_min":2,"flag":1,"level":1,"start_time":1766735700000,"end_time":1766735759000},{"score":2,"score_max":3,"score_min":2,"flag":1,"level":1,"start_time":1766735640000,"end_time":1766735699000},{"score":4,"score_max":6,"score_min":3,"flag":1,"level":1,"start_time":1766735400000,"end_time":1766735459000},{"score":5,"score_max":11,"score_min":2,"flag":1,"level":1,"start_time":1766735340000,"end_time":1766735399000},{"score":0,"score_max":2,"score_min":0,"flag":1,"level":1,"start_time":1766735280000,"end_time":1766735339000},{"score":0,"score_max":0,"score_min":0,"flag":1,"level":1,"start_time":1766735220000,"end_time":1766735279000},{"score":3,"score_max":9,"score_min":0,"flag":1,"level":1,"start_time":1766735160000,"end_time":1766735219000},{"score":5,"score_max":9,"score_min":4,"flag":1,"level":1,"start_time":1766735100000,"end_time":1766735159000},{"score":9,"score_max":16,"score_min":4,"flag":1,"level":1,"start_time":1766734860000,"end_time":1766734919000},{"score":2,"score_max":3,"score_min":2,"flag":1,"level":1,"start_time":1766734800000,"end_time":1766734859000},{"score":0,"score_max":1,"score_min":0,"flag":1,"level":1,"start_time":1766734680000,"end_time":1766734739000}]