[{"score":0,"score_max":0,"score_min":0,"flag":1,"level":1,"start_time":1766714340000,"end_time":1766714399000},{"score":0,"score_max":0,"score_min":0,"flag":1,"level":1,"start_time":1766714280000,"end_time":1766714339000},{"score":0,"score_max":0,"score_min":0,"flag":1,"level":1,"start_time":1766714220000,"end_time":1766714279000},{"score":0,"score_max":0,"score_min":0,"flag":1,"level":1,"start_time":1766714160000,"end_time":1766714219000},{"score":0,"score_max":0,"score_min":0,"flag":1,"level":1,"start_time":1766714100000,"end_time":1766714159000},{"score":0,"score_max":0,"score_min":0,"flag":1,"level":1,"start_time":1766714040000,"end_time":1766714099000},{"score":0,"score_max":0,"score_min":0,"flag":1,"level":1,"start_time":1766713980000,"end_time":1766714039000},{"score":0,"score_max":0,"score_min":0,"flag":1,"level":1,"start_time":1766713920000,"end_time":1766713979000},{"score":0,"score_max":0,"score_min":0,"flag":1,"level":1,"start_time":1766713860000,"end_time":1766713919000},{"score":0,"score_max":0,"score_min":0,"flag":1,"level":1,"start_time":1766713800000,"end_time":1766713859000},{"score":0,"score_max":0,"score_min":0,"flag":1,"level":1,"start_time":1766713740000,"end_time":1766713799000},{"score":0,"score_max":0,"score_min":0,"flag":1,"level":1,"start_time":1766713680000,"end_time":1766713739000},{"score":0,"score_max":0,"score_min":0,"flag":1,"level":1,"start_time":1766713620000,"end_time":1766713679000},{"score":0,"score_max":0,"score_min":0,"flag":1,"level":1,"start_time":1766713560000,"end_time":1766713619000},{"score":0,"score_max":2,"score_min":0,"flag":1,"level":1,"start_time":1766713500000,"end_time":1766713559000},{"score":2,"score_max":3,"score_min":2,"flag":1,"level":1,"start_time":1766713440000,"end_time":1766713499000},{"score":2,"score_max":6,"score_min":1,"flag":1,"level":1,"start_time":1766713380000,"end_time":1766713439000},{"score":0,"score_max":1,"score_min":0,"flag":1,"level":1,"start_time":1766713320000,"end_time":1766713379000},{"score":0,"score_max":0,"score_min":0,"flag":1,"level":1,"start_time":1766713260000,"end_time":1766713319000},{"score":0,"score_max":0,"score_min":0,"flag":1,"level":1,"start_time":1766713200000,"end_time":1766713259000},{"score":0,"score_max":0,"score_min":0,"flag":1,"level":1,"start_time":1766713140000,"end_time":1766713199000},{"score":0,"score_max":0,"score_min":0,"flag":1,"level":1,"start_time":1766713080000,"end_time":1766713139000},{"score":0,"score_max":0,"score_min":0,"flag":1,"level":1,"start_time":1766713020000,"end_time":1766713079000},{"score":0,"score_max":0,"score_min":0,"flag":1,"level":1,"start_time":1766712960000,"end_time":1766713019000},{"score":0,"score_max":0,"score_min":0,"flag":1,"level":1,"start_time":1766712900000,"end_time":1766712959000},{"score":0,"score_max":0,"score_min":0,"flag":1,"level":1,"start_time":1766712840000,"end_time":1766712899000},{"score":0,"score_max":0,"score_min":0,"flag":1,"level":1,"start_time":1766712780000,"end_time":1766712839000},{"score":0,"score_max":0,"score_min":0,"flag":1,"level":1,"start_time":1766712720000,"end_time":1766712779000},{"score":0,"score_max":0,"score_min":0,"flag":1,"level":1,"start_time":1766712660000,"end_time":1766712719000},{"score":0,"score_max":0,"score_min":0,"flag":1,"level":1,"start_time":1766712600000,"end_time":1766712659000},{"score":0,"score_max":0,"score_min":0,"flag":1,"level":1,"start_time":1766712540000,"end_time":1766712599000},{"score":0,"score_max":0,"score_min":0,"flag":1,"level":1,"start_time":1766712480000,"end_time":1766712539000},{"score":0,"score_max":0,"score_min":0,"flag":1,"level":1,"start_time":1766712420000,"end_time":1766712479000},{"score":0,"score_max":0,"score_min":0,"flag":1,"level":1,"start_time":1766712360000,"end_time":1766712419000},{"score":0,"score_max":2,"score_min":0,"flag":1,"level":1,"start_time":1766712300000,"end_time":1766712359000},{"score":0,"score_max":2,"score_min":0,"flag":1,"level":1,"start_time":1766712240000,"end_time":1766712299000},{"score":0,"score_max":0,"score_min":0,"flag":1,"level":1,"start_time":1766712180000,"end_time":1766712239000},{"score":0,"score_max":1,"score_min":0,"flag":1,"level":1,"start_time":1766712120000,"end_time":1766712179000},{"score":0,"score_max":1,"score_min":0,"flag":1,"level":1,"start_time":1766712060000,"end_time":1766712119000},{"score":0,"score_max":0,"score_min":0,"flag":1,"level":1,"start_time":1766712000000,"end_time":1766712059000},{"score":0,"score_max":0,"score_min":0,"flag":1,"level":1,"start_time":1766711940000,"end_time":1766711999000},{"score":0,"score_max":0,"score_min":0,"flag":1,"level":1,"start_time":1766711880000,"end_time":1766711939000},{"score":8,"score_max":17,"score_min":0,"flag":1,"level":1,"start_time":1766710980000,"end_time":1766711039000},{"score":18,"score_max":18,"score_min":18,"flag":1,"level":1,"start_time":1766710920000,"end_time":1766710979000},{"score":11,"score_max":19,"score_min":5,"flag":1,"level":1,"start_time":1766710860000,"end_time":1766710919000}]